string_schema/__init__.py
string_schema/py.typed
string_schema/utilities.py
string_schema/core/__init__.py
string_schema/core/builders.py
string_schema/core/fields.py
string_schema/core/validators.py
string_schema/examples/__init__.py
string_schema/examples/presets.py
string_schema/examples/recipes.py
string_schema/integrations/__init__.py
string_schema/integrations/json_schema.py
string_schema/integrations/openapi.py
string_schema/integrations/pydantic.py
string_schema/integrations/reverse.py
string_schema/parsing/__init__.py
string_schema/parsing/optimizer.py
string_schema/parsing/string_parser.py
string_schema/parsing/syntax.py
string_schema-0.1.6.dist-info/licenses/LICENSE
string_schema-0.1.6.dist-info/METADATA
string_schema-0.1.6.dist-info/WHEEL
string_schema-0.1.6.dist-info/top_level.txt
string_schema-0.1.6.dist-info/RECORD
