Metadata-Version: 2.4
Name: string-schema
Version: 0.1.6
Summary: A simple, LLM-friendly schema definition library for converting string syntax to structured schemas
Home-page: https://github.com/xychenmsn/string-schema
Author: Michael Chen
Author-email: Michael Chen <xychen@msn.com>
Maintainer-email: Michael Chen <xychen@msn.com>
License-Expression: MIT
Project-URL: Homepage, https://github.com/xychenmsn/string-schema
Project-URL: Documentation, https://github.com/xychenmsn/string-schema#readme
Project-URL: Repository, https://github.com/xychenmsn/string-schema
Project-URL: Bug Reports, https://github.com/xychenmsn/string-schema/issues
Project-URL: Changelog, https://github.com/xychenmsn/string-schema/releases
Keywords: schema,validation,json,llm,ai,data-extraction,pydantic
Classifier: Development Status :: 3 - Alpha
Classifier: Intended Audience :: Developers
Classifier: Operating System :: OS Independent
Classifier: Programming Language :: Python :: 3
Classifier: Programming Language :: Python :: 3.11
Classifier: Programming Language :: Python :: 3.12
Classifier: Programming Language :: Python :: 3.13
Classifier: Topic :: Software Development :: Libraries :: Python Modules
Classifier: Topic :: Text Processing :: Markup
Classifier: Topic :: Utilities
Classifier: Typing :: Typed
Requires-Python: >=3.11
License-File: LICENSE
Requires-Dist: pydantic>=2.0.0
Requires-Dist: email-validator>=2.0.0
Provides-Extra: dev
Requires-Dist: pytest>=7.0.0; extra == "dev"
Requires-Dist: pytest-cov>=4.0.0; extra == "dev"
Requires-Dist: black>=22.0.0; extra == "dev"
Requires-Dist: isort>=5.0.0; extra == "dev"
Requires-Dist: flake8>=5.0.0; extra == "dev"
Requires-Dist: mypy>=1.0.0; extra == "dev"
Requires-Dist: pre-commit>=2.20.0; extra == "dev"
Provides-Extra: docs
Requires-Dist: sphinx>=5.0.0; extra == "docs"
Requires-Dist: sphinx-rtd-theme>=1.0.0; extra == "docs"
Requires-Dist: myst-parser>=0.18.0; extra == "docs"
Dynamic: author
Dynamic: home-page
Dynamic: license-file
Dynamic: requires-python
